__init__.py
setup.py
enhanced_reports/__init__.py
enhanced_reports/browser_console_manager.py
enhanced_reports/common_utils.py
enhanced_reports/config.py
enhanced_reports/core.py
enhanced_reports/screenshot_manager.py
enhanced_reports/video_manager.py
enhanced_reports/report_libs/__init__.py
enhanced_reports/report_libs/allure_pytest_bdd.py
enhanced_reports/report_libs/pytest-testrail-client.py
pytest_enhanced_reports-1.2.3.dist-info/LICENSE.txt
pytest_enhanced_reports-1.2.3.dist-info/METADATA
pytest_enhanced_reports-1.2.3.dist-info/WHEEL
pytest_enhanced_reports-1.2.3.dist-info/top_level.txt
pytest_enhanced_reports-1.2.3.dist-info/RECORD
