Metadata-Version: 2.1
Name: pytest-enhanced-reports
Version: 1.2.3
Summary: Enhanced test reports for pytest
Author-email: NewPage Solutions <InnovationDesk@newpage.io>
Project-URL: Homepage, https://newpage-solutions-inc.github.io/pytest-enhanced-reports/
Project-URL: Bug Tracker, https://github.com/NewPage-Solutions-Inc/pytest-enhanced-reports/issues
Classifier: Programming Language :: Python :: 3
Classifier: License :: OSI Approved :: MIT License
Classifier: Operating System :: OS Independent
Requires-Python: >=3.7
License-File: LICENSE.txt
